{
 "id": "edition-onmuhasebe",
 "title": "Ön Muhasebe Edition",
 "subtitle": "Accounting Stack'in SMB self-serve paketlenmesi: e-fatura odaklı onboarding, sadeleştirilmiş ekranlar, muhasebeci-paylaşım akışı.",
 "cluster": "aday",
 "order": 1,
 "icon": "ph-receipt",
 "granularity": "kaya",
 "state": "aday",
 "badge": "EDITION",
 "tags": [
  "edition",
  "ux",
  "accounting"
 ],
 "related": [
  "stack-accounting",
  "stack-editions"
 ],
 "parent": "s-accounting",
 "relations": [
  {
   "type": "extends",
   "target": "s-accounting"
  },
  {
   "type": "uses",
   "target": "stack-editions"
  }
 ],
 "enrich": {
  "info": "Edition sözleşmesi: core module seti ve kod aynıdır; fark UI estetiği, UX akışı ve pazara çıkış paketindedir (landing, fiyat, onboarding). Fonksiyon eklemek Edition işi değildir — o ihtiyaç parent stack'e gider."
 },
 "blocks": [
  {
   "type": "image",
   "src": "/assets/cards/edition-onmuhasebe.svg",
   "alt": "Ön Muhasebe Edition — edition (UX paketi) kartı: parent stack ve fark alanları",
   "caption": "Ön Muhasebe Edition — aday katalog kaydı"
  },
  {
   "type": "heading",
   "level": 2,
   "text": "Kapsam"
  },
  {
   "type": "kv-row",
   "pairs": [
    {
     "key": "Temel",
     "value": "{{ref:stack-accounting}} — defter/fatura/vergi core'u"
    },
    {
     "key": "UI farkı",
     "value": "Muhasebe jargonu gizli: 'kestiğim faturalar / aldığım faturalar' dili; tek sayfa nakit görünümü"
    },
    {
     "key": "UX farkı",
     "value": "5 dakikada ilk e-fatura; banka bağlantısı sihirbazla; muhasebeciye salt-okur davet"
    },
    {
     "key": "Hedef alıcı",
     "value": "1-20 kişilik işletme sahibi — muhasebe bilmeyen"
    }
   ]
  },
  {
   "type": "heading",
   "level": 2,
   "text": "Pazar Çekişi — Reklamlı Kanal"
  },
  {
   "type": "callout",
   "variant": "info",
   "label": "Ücretli kanal",
   "body": "Paraşüt kategorisi: reklamla dönen pazar; dönüşüm UI sadeliğiyle kazanılır."
  }
 ]
}