{
 "__generated": "tools/migrate — elle düzenleme yasak (04 §1)",
 "schemaVersion": "1.0",
 "page": {
  "id": "page-edu-u01-yazilim",
  "sourceId": "edu-u01",
  "slug": "egitim/edu-u01-yazilim",
  "title": "Yazılım nedir? — temel zihinsel model",
  "summary": "Kod, derleyici, runtime, framework, monolit ve meta-framework — bu projenin yazılım dünyasındaki yeri.",
  "categoryId": "egitim",
  "tags": [
   "education",
   "u01",
   "temel"
  ],
  "meta": {
   "granularity": "buyuk-tas",
   "state": "ok"
  },
  "related": [
   "page-edu-overview",
   "page-edu-u02-veri-tip",
   "page-philosophy"
  ],
  "blocks": [
   {
    "id": "block-edu-u01-yazilim-ozet",
    "type": "callout",
    "variant": "info",
    "title": "Özet",
    "segments": [
     {
      "type": "term",
      "text": "Kod",
      "termId": "term-kod-edu-u01-yazilim"
     },
     {
      "type": "text",
      "text": ", "
     },
     {
      "type": "term",
      "text": "derleyici",
      "termId": "term-derleyici-edu-u01-yazilim"
     },
     {
      "type": "text",
      "text": ", runtime, "
     },
     {
      "type": "term",
      "text": "framework",
      "termId": "term-framework-edu-u01-yazilim"
     },
     {
      "type": "text",
      "text": ", "
     },
     {
      "type": "term",
      "text": "monolit",
      "termId": "term-monolit-edu-u01-yazilim"
     },
     {
      "type": "text",
      "text": " ve "
     },
     {
      "type": "term",
      "text": "meta-framework",
      "termId": "term-meta-framework-edu-u01-yazilim"
     },
     {
      "type": "text",
      "text": " — bu projenin yazılım dünyasındaki yeri."
     }
    ]
   },
   {
    "id": "block-edu-u01-yazilim-lh",
    "type": "lessonHeader",
    "unit": "Ünite 01",
    "title": "Yazılım nedir? Bu projenin yeri ne?",
    "level": "baslangic",
    "durationMin": 45,
    "prereq": [],
    "goals": [
     "Kod, derleme, çalışma zamanı, kütüphane, framework farkını anlatabilirsin.",
     "Monolit, mikro-servis, meta-framework arasındaki farkı bilirsin.",
     "Bu projenin neden 'meta-framework' olduğunu açıklayabilirsin."
    ]
   },
   {
    "id": "block-edu-u01-yazilim-h-kavramlar-bu-unitede-gececek-tum-terimler",
    "type": "heading",
    "level": 4,
    "text": "Kavramlar — bu ünitede geçecek tüm terimler"
   },
   {
    "id": "block-edu-u01-yazilim-h-anlatim-kod-dan-meta-framework-e",
    "type": "heading",
    "level": 4,
    "text": "Anlatım — kod'dan meta-framework'e"
   },
   {
    "id": "block-edu-u01-yazilim-p",
    "type": "paragraph",
    "segments": [
     {
      "type": "strong",
      "text": "Kod"
     },
     {
      "type": "text",
      "text": ", bilgisayara ne yapacağını söyleyen metindir. Tek başına çalışmaz; bir "
     },
     {
      "type": "strong",
      "text": "çalışma zamanı"
     },
     {
      "type": "text",
      "text": " (runtime) gerekir. Çoğu "
     },
     {
      "type": "strong",
      "text": "kütüphane"
     },
     {
      "type": "text",
      "text": " kullanır; az kısmı bir "
     },
     {
      "type": "strong",
      "text": "framework"
     },
     {
      "type": "text",
      "text": " içinde yaşar."
     }
    ]
   },
   {
    "id": "block-edu-u01-yazilim-note",
    "type": "callout",
    "variant": "info",
    "title": "Not",
    "segments": [
     {
      "type": "text",
      "text": "Library = sen çağırırsın. Framework = framework seni çağırır."
     }
    ]
   },
   {
    "id": "block-edu-u01-yazilim-p-2",
    "type": "paragraph",
    "segments": [
     {
      "type": "text",
      "text": "Bir framework'ün üzerine "
     },
     {
      "type": "strong",
      "text": "ürün"
     },
     {
      "type": "text",
      "text": " koymak yetebilir (e-ticaret sitesi). Ama biz "
     },
     {
      "type": "strong",
      "text": "15 farklı ürün"
     },
     {
      "type": "text",
      "text": " koyacağız (HRMS, e-ticaret, muhasebe, …). Bunun için framework'ün kendisini parametrize edilebilir yapmamız lazım — buna "
     },
     {
      "type": "strong",
      "text": "meta-framework"
     },
     {
      "type": "text",
      "text": " denir. Sen yeni bir 'Müşteri Şikayeti' tipi tanımlıyorsun, ortalık otomatik kuruluyor."
     }
    ]
   },
   {
    "id": "block-edu-u01-yazilim-note-2",
    "type": "callout",
    "variant": "info",
    "title": "Not",
    "segments": [
     {
      "type": "text",
      "text": "Meta-framework = framework yazmaya yarayan framework."
     }
    ]
   },
   {
    "id": "block-edu-u01-yazilim-story",
    "type": "useCase",
    "title": "İş sahibi",
    "scenario": [
     {
      "type": "text",
      "text": "Bir SaaS müşterisi 'kendi şirketim için CRM yapın' der."
     }
    ],
    "outcome": [
     {
      "type": "text",
      "text": "Meta-framework'te yeni ArcheType'lar tanımlayarak ona özel CRM çıkar — kod yazmadan."
     }
    ]
   },
   {
    "id": "block-edu-u01-yazilim-grid",
    "type": "cardGrid",
    "columns": 3,
    "cards": [
     {
      "icon": "ph-toolbox",
      "title": "Library",
      "tone": "neutral",
      "segments": [
       {
        "type": "text",
        "text": "Sen çağırırsın. Örn: "
       },
       {
        "type": "code",
        "text": "dayjs.format(date)"
       },
       {
        "type": "text",
        "text": " — tarihi formatlamak için fonksiyon."
       }
      ]
     },
     {
      "icon": "ph-stack",
      "title": "Framework",
      "tone": "neutral",
      "segments": [
       {
        "type": "text",
        "text": "Framework seni çağırır. Örn: Django senin "
       },
       {
        "type": "code",
        "text": "view()"
       },
       {
        "type": "text",
        "text": " fonksiyonunu HTTP isteği gelince çağırır."
       }
      ]
     },
     {
      "icon": "ph-cube",
      "title": "Meta-framework",
      "tone": "good",
      "segments": [
       {
        "type": "text",
        "text": "Sen ArcheType tanımlarsın → framework DB+API+UI üretir. Kod yazmadan ürün doğar."
       }
      ]
     }
    ]
   },
   {
    "id": "block-edu-u01-yazilim-h-monolit-mikro-servis-moduler-monolit-kararimiz-neden",
    "type": "heading",
    "level": 4,
    "text": "Monolit, mikro-servis, modüler monolit — kararımız neden?"
   },
   {
    "id": "block-edu-u01-yazilim-table",
    "type": "table",
    "columns": [
     "Yaklaşım",
     "Avantaj",
     "Sakınca",
     "Bizim için"
    ],
    "rows": [
     [
      [
       {
        "type": "text",
        "text": "Monolit"
       }
      ],
      [
       {
        "type": "text",
        "text": "Basit deploy, hızlı iteration"
       }
      ],
      [
       {
        "type": "text",
        "text": "Modüller birbirine sızar, refactor zor"
       }
      ],
      [
       {
        "type": "text",
        "text": "Eksik — modüler bir yana iter"
       }
      ]
     ],
     [
      [
       {
        "type": "text",
        "text": "Mikro-servis"
       }
      ],
      [
       {
        "type": "text",
        "text": "Ekip bağımsız, ayrı ölçek"
       }
      ],
      [
       {
        "type": "text",
        "text": "Ağ karmaşası, operasyon yükü 10×"
       }
      ],
      [
       {
        "type": "text",
        "text": "Erken; küçük ekipte boğar"
       }
      ]
     ],
     [
      [
       {
        "type": "text",
        "text": "Modüler monolit (ok)"
       }
      ],
      [
       {
        "type": "text",
        "text": "Tek deploy + sıkı modül sınırı"
       }
      ],
      [
       {
        "type": "text",
        "text": "Disiplin gerektirir"
       }
      ],
      [
       {
        "type": "text",
        "text": "Kararımız (ok)"
       }
      ]
     ]
    ]
   },
   {
    "id": "block-edu-u01-yazilim-co",
    "type": "callout",
    "variant": "tip",
    "title": "Neden bu seçim?",
    "segments": [
     {
      "type": "term",
      "text": "Modüler monolit",
      "termId": "term-moduler-monolit-edu-u01-yazilim"
     },
     {
      "type": "text",
      "text": ", "
     },
     {
      "type": "strong",
      "text": "70+ ürün hedefini (ilk dalga 15) tek ekip + tek deploy"
     },
     {
      "type": "text",
      "text": " ile taşımanın matematiğidir. Frappe (ERPNext), Odoo, Salesforce hepsi bu paterni izledi. Mikro-servise geçiş gerekirse modüller hazır sınırlı — kesim kolay."
     }
    ]
   },
   {
    "id": "block-edu-u01-yazilim-p-3",
    "type": "paragraph",
    "segments": [
     {
      "type": "strong",
      "text": "Anti-pattern:"
     },
     {
      "type": "text",
      "text": " "
     },
     {
      "type": "term",
      "text": "Mikro-servis",
      "termId": "term-mikro-servis-edu-u01-yazilim"
     },
     {
      "type": "text",
      "text": " ile başlayıp her özellik için yeni servis açmak. Sonuç: 40 mikro-servis, 1 ekip, ölü proje. Önce monolit; ölçek dayatınca böl."
     }
    ]
   },
   {
    "id": "block-edu-u01-yazilim-h-adim-adim-bir-yeni-kayit-ozelligi-bizim-sistemde-nasil-calisir",
    "type": "heading",
    "level": 4,
    "text": "Adım-adım: bir 'Yeni Kayıt' özelliği bizim sistemde nasıl çalışır?"
   },
   {
    "id": "block-edu-u01-yazilim-steps",
    "type": "stepList",
    "steps": [
     {
      "title": "Sen ArcheType tanımlarsın",
      "segments": [
       {
        "type": "text",
        "text": "Admin panelden 'Müşteri Şikayeti' isimli yeni bir ArcheType oluştururşun. Alanlar: konu, açıklama, öncelik."
       }
      ]
     },
     {
      "title": "Framework devralır",
      "segments": [
       {
        "type": "text",
        "text": "Anında: DB'de "
       },
       {
        "type": "code",
        "text": "tabMusteriSikayeti"
       },
       {
        "type": "text",
        "text": " tablosu, REST endpoint ("
       },
       {
        "type": "code",
        "text": "/api/resource/MusteriSikayeti"
       },
       {
        "type": "text",
        "text": "), admin formu, audit log, search index oluşur."
       }
      ]
     },
     {
      "title": "Kullanıcı kayıt girer",
      "segments": [
       {
        "type": "text",
        "text": "Form doldurur → REST POST → DB INSERT → audit log → event bus 'yeni şikayet' yayını → bildirim worker maile düşer."
       }
      ]
     },
     {
      "title": "Modül tepki verir",
      "segments": [
       {
        "type": "text",
        "text": "Helpdesk modülü event'i dinler; otomatik ticket açar, atama yapar."
       }
      ]
     },
     {
      "title": "Sen kod yazmadın",
      "segments": [
       {
        "type": "text",
        "text": "Bütün bu zincirin tek girdisi: bir ArcheType tanımı + bir modül manifest."
       }
      ]
     }
    ]
   },
   {
    "id": "block-edu-u01-yazilim-chk",
    "type": "checklist",
    "title": "Bu üniteyi anladığımı nereden anlarım?",
    "storageKey": "edu.u01",
    "items": [
     {
      "segments": [
       {
        "type": "text",
        "text": "Kod, derleyici, runtime, library, framework arasındaki farkı bir başkasına anlatabilirim."
       }
      ]
     },
     {
      "segments": [
       {
        "type": "text",
        "text": "Library ve framework farkını 'kim kimi çağırır' üzerinden açıklayabilirim."
       }
      ]
     },
     {
      "segments": [
       {
        "type": "text",
        "text": "Meta-framework'ün neden 70+ ürün hedefimizle (ilk dalga 15) örtüştüğünü söyleyebilirim."
       }
      ]
     },
     {
      "segments": [
       {
        "type": "text",
        "text": "Modüler monolitin neden tercihimiz olduğunu 1-2 cümleyle özetleyebilirim."
       }
      ]
     },
     {
      "segments": [
       {
        "type": "text",
        "text": "Bir ArcheType tanımı yapıldığında framework'ün ne ürettiğini sıralayabilirim (DB tablo, REST, form, audit, …). — 5 çıktıyı sayman yeterli."
       }
      ]
     }
    ]
   },
   {
    "id": "block-edu-u01-yazilim-h-mini-proje-zorunlu-degil",
    "type": "heading",
    "level": 4,
    "text": "Mini-proje (zorunlu değil)"
   },
   {
    "id": "block-edu-u01-yazilim-p-4",
    "type": "paragraph",
    "segments": [
     {
      "type": "text",
      "text": "Defterine 3 sütun yaz: "
     },
     {
      "type": "strong",
      "text": "Library / Framework / Meta-framework"
     },
     {
      "type": "text",
      "text": ". Şu araçları sınıflandır: jQuery, Django, React, Frappe, Odoo, Vue, Tailwind, Salesforce, dayjs, FastAPI. (Cevaplar "
     },
     {
      "type": "strong",
      "text": "?"
     },
     {
      "type": "text",
      "text": " butonunda.)"
     }
    ]
   },
   {
    "id": "block-edu-u01-yazilim-p-5",
    "type": "paragraph",
    "segments": [
     {
      "type": "strong",
      "text": "Cevap:"
     }
    ]
   },
   {
    "id": "block-edu-u01-yazilim-list",
    "type": "list",
    "ordered": false,
    "items": [
     [
      {
       "type": "strong",
       "text": "Library"
      },
      {
       "type": "text",
       "text": ": jQuery, React (UI library), Vue (UI library), Tailwind (CSS library), dayjs"
      }
     ],
     [
      {
       "type": "strong",
       "text": "Framework"
      },
      {
       "type": "text",
       "text": ": Django, FastAPI"
      }
     ],
     [
      {
       "type": "strong",
       "text": "Meta-framework"
      },
      {
       "type": "text",
       "text": ": Frappe, Odoo, Salesforce"
      }
     ]
    ]
   },
   {
    "id": "block-edu-u01-yazilim-p-6",
    "type": "paragraph",
    "segments": [
     {
      "type": "text",
      "text": "React'in 'framework mi library mi' tartışması var; resmi olarak 'library' diye geçer çünkü sen çağırırsın."
     }
    ]
   },
   {
    "id": "block-edu-u01-yazilim-co-2",
    "type": "callout",
    "variant": "info",
    "title": "Sonraki ünite",
    "segments": [
     {
      "type": "ref",
      "text": "edu-u02",
      "refId": "edu-u02"
     },
     {
      "type": "text",
      "text": " — Veri ve Tipler. Bilgisayarın bir 'Müşteri Şikayeti'ni hangi sayılar/harfler ile sakladığını öğreneceğiz."
     }
    ]
   },
   {
    "id": "block-edu-u01-yazilim-h-derinlemesine",
    "type": "heading",
    "level": 2,
    "text": "Derinlemesine"
   },
   {
    "id": "block-edu-u01-yazilim-p-7",
    "type": "paragraph",
    "segments": [
     {
      "type": "text",
      "text": "Kod, derleyici, runtime, framework, monolit ve meta-framework — bu projenin yazılım dünyasındaki yeri."
     }
    ]
   },
   {
    "id": "block-edu-u01-yazilim-h-yedi-soruda",
    "type": "heading",
    "level": 2,
    "text": "Bu konu yedi soruda"
   },
   {
    "id": "block-edu-u01-yazilim-lesson",
    "type": "definitionList",
    "items": [
     {
      "term": "Ne?",
      "definition": [
       {
        "type": "text",
        "text": "Ünite 01 — Yazılım nedir? Kod, derleyici, "
       },
       {
        "type": "term",
        "text": "çalışma zamanı",
        "termId": "term-calisma-zamani-edu-u01-yazilim"
       },
       {
        "type": "text",
        "text": ", "
       },
       {
        "type": "term",
        "text": "kütüphane",
        "termId": "term-kutuphane-edu-u01-yazilim"
       },
       {
        "type": "text",
        "text": ", çerçeve, monolit, mikroservis kavramları."
       }
      ]
     },
     {
      "term": "Niçin?",
      "definition": [
       {
        "type": "text",
        "text": "Bu temel kavramları bilmeden ileriki üniteler havada kalır."
       }
      ]
     },
     {
      "term": "Nasıl?",
      "definition": [
       {
        "type": "text",
        "text": "Her terim Türkçe karşılığıyla, gerçek hayat örnekleriyle açıklanır."
       }
      ]
     },
     {
      "term": "Nerede?",
      "definition": [
       {
        "type": "text",
        "text": "Müfredatın ilk ünitesi — atlanamaz."
       }
      ]
     },
     {
      "term": "Ne zaman?",
      "definition": [
       {
        "type": "text",
        "text": "Sıfırdan başlayan herkes ilk burayı okur."
       }
      ]
     },
     {
      "term": "Kim?",
      "definition": [
       {
        "type": "text",
        "text": "Sen — yazılıma yeni başlayan."
       }
      ]
     },
     {
      "term": "Analoji",
      "definition": [
       {
        "type": "text",
        "text": "Yabancı bir dilin alfabesini öğrenmek: alfabe olmadan kelime, kelime olmadan cümle olmaz."
       }
      ]
     }
    ]
   }
  ]
 }
}