{
 "__generated": "tools/migrate — elle düzenleme yasak (04 §1)",
 "schemaVersion": "1.0",
 "page": {
  "id": "page-landx-l3-application",
  "sourceId": "landx-l3",
  "slug": "stack/landx-l3-application",
  "title": "LandX L3 — Uygulama Yüzeyi (Application Surface)",
  "summary": "S01–S06. Auto REST API, admin UI engine, form/validation, workflow, notification, search.",
  "categoryId": "stack",
  "tags": [
   "landx",
   "application",
   "rest",
   "admin-ui",
   "workflow"
  ],
  "meta": {
   "badge": "LandX L3 — 6 modül"
  },
  "related": [],
  "blocks": [
   {
    "id": "block-landx-l3-application-ozet",
    "type": "callout",
    "variant": "info",
    "title": "Özet",
    "segments": [
     {
      "type": "text",
      "text": "S01–S06. Auto "
     },
     {
      "type": "term",
      "text": "REST",
      "termId": "term-rest-landx-l3-application"
     },
     {
      "type": "text",
      "text": " API, admin UI engine, form/validation, workflow, notification, search."
     }
    ]
   },
   {
    "id": "block-landx-l3-application-p",
    "type": "paragraph",
    "segments": [
     {
      "type": "text",
      "text": "L3 katmanı: DocType tanımından otomatik olarak üretilen REST API, admin UI, form, validation, workflow, notification ve hybrid search yüzeyleri."
     }
    ]
   },
   {
    "id": "block-landx-l3-application-feat",
    "type": "definitionList",
    "items": [
     {
      "term": "S01 — Auto REST API Engine",
      "definition": [
       {
        "type": "strong",
        "text": "Faz 1 · P0 · Application Squad."
       },
       {
        "type": "text",
        "text": " DocType'tan otomatik REST endpoint (CRUD + filter + bulk). Aynı tanımdan OpenAPI spec, MCP tool listesi, "
       },
       {
        "type": "term",
        "text": "GraphQL",
        "termId": "term-graphql-landx-l3-application"
       },
       {
        "type": "text",
        "text": " schema türetilir. *Capabilities:* CRUD Endpoint Generation, OpenAPI Spec, Bulk & Batch Operations, Pagination & Cursor, Webhooks. *KPI:* DocType → endpoint p95 <60sn, OpenAPI conformance %100, endpoint latency p95 <120ms."
       }
      ]
     },
     {
      "term": "S02 — Auto Admin UI Engine",
      "definition": [
       {
        "type": "strong",
        "text": "Faz 2 · P0 · Application Squad."
       },
       {
        "type": "text",
        "text": " DocType'tan auto-generated admin UI: list, detail, form, bulk action, filter side-panel. Flowbite + React Router v7. AI co-pilot her ekranda. *Capabilities:* List View · Detail View & Form · Bulk Actions · Saved Views · AI Co-pilot. *KPI:* DocType → çalışır UI <2dk, custom override penalty <%10, Lighthouse a11y >90."
       }
      ]
     },
     {
      "term": "S03 — Form & Validation Framework",
      "definition": [
       {
        "type": "strong",
        "text": "Faz 2 · P1 · Application Squad."
       },
       {
        "type": "text",
        "text": " Form lifecycle, server-side + client-side validation, conditional fields, wizard flows, AI auto-fill, draft autosave. Tüm validation kuralları MCP tool olarak dış dünyaya da expose edilir."
       }
      ]
     },
     {
      "term": "S04 — Workflow & State Machine",
      "definition": [
       {
        "type": "strong",
        "text": "Faz 3 · P1 · Application Squad."
       },
       {
        "type": "text",
        "text": " DocType yaşam döngüsü için deklaratif state machine. Her transition: guard, action, side-effect, audit. Agent transition'ı tetikleyebilir (scope izinliyse). Bizim eşdeğer: "
       },
       {
        "type": "ref",
        "text": "l1-workflow",
        "refId": "l1-workflow"
       },
       {
        "type": "text",
        "text": "."
       }
      ]
     },
     {
      "term": "S05 — Notification Center",
      "definition": [
       {
        "type": "strong",
        "text": "Faz 3 · P1 · Application Squad."
       },
       {
        "type": "text",
        "text": " Multi-channel bildirim: in-app, email, SMS, push, "
       },
       {
        "type": "term",
        "text": "webhook",
        "termId": "term-webhook-landx-l3-application"
       },
       {
        "type": "text",
        "text": ", agent ping. Template management, user preferences, digest, throttle. *KPI:* Email delivery >%98, in-app render p95 <500ms. Bizim eşdeğer: "
       },
       {
        "type": "ref",
        "text": "l1-notification",
        "refId": "l1-notification"
       },
       {
        "type": "text",
        "text": "."
       }
      ]
     },
     {
      "term": "S06 — Search & Discovery",
      "definition": [
       {
        "type": "strong",
        "text": "Faz 3 · P1 · Application + AI Squad."
       },
       {
        "type": "text",
        "text": " DocType genel arama yüzeyi. Hybrid retrieval (BM25 + vector), faceted filter, query understanding (NL → structured), saved searches, alert subscriptions. *KPI:* NDCG@10 >0.78, query latency p95 <250ms. Bizim eşdeğer: "
       },
       {
        "type": "ref",
        "text": "l1-search",
        "refId": "l1-search"
       },
       {
        "type": "text",
        "text": "."
       }
      ]
     }
    ]
   },
   {
    "id": "block-landx-l3-application-co",
    "type": "callout",
    "variant": "info",
    "title": "Bizim framework ile örtüşme",
    "segments": [
     {
      "type": "text",
      "text": "L3 modülleri büyük ölçüde bizim Layer 1 in-tree katmanına denk gelir. S01 → REST autogen ("
     },
     {
      "type": "ref",
      "text": "l1-misc",
      "refId": "l1-misc"
     },
     {
      "type": "text",
      "text": "), S02 → Admin UI ("
     },
     {
      "type": "ref",
      "text": "s-cms",
      "refId": "s-cms"
     },
     {
      "type": "text",
      "text": " authoring + Layer 1 reporting), S03 → form, S04 → "
     },
     {
      "type": "ref",
      "text": "l1-workflow",
      "refId": "l1-workflow"
     },
     {
      "type": "text",
      "text": ", S05 → "
     },
     {
      "type": "ref",
      "text": "l1-notification",
      "refId": "l1-notification"
     },
     {
      "type": "text",
      "text": ", S06 → "
     },
     {
      "type": "ref",
      "text": "l1-search",
      "refId": "l1-search"
     },
     {
      "type": "text",
      "text": ".\n\nFark: LandX'te bu modüller agent-aware. Her validation MCP tool olarak expose, her workflow transition agent tetikleyebilir, search hem human hem agent için. Bizim Layer 1'i AI Stack ("
     },
     {
      "type": "ref",
      "text": "s-ai",
      "refId": "s-ai"
     },
     {
      "type": "text",
      "text": ") ile birleştirdiğinde aynı sonuç."
     }
    ]
   },
   {
    "id": "block-landx-l3-application-h-derinlemesine",
    "type": "heading",
    "level": 2,
    "text": "Derinlemesine"
   },
   {
    "id": "block-landx-l3-application-p-2",
    "type": "paragraph",
    "segments": [
     {
      "type": "text",
      "text": "S01–S06. Auto REST API, admin UI engine, form/validation, workflow, notification, search."
     }
    ]
   },
   {
    "id": "block-landx-l3-application-h-yedi-soruda",
    "type": "heading",
    "level": 2,
    "text": "Bu konu yedi soruda"
   },
   {
    "id": "block-landx-l3-application-lesson",
    "type": "definitionList",
    "items": [
     {
      "term": "Ne?",
      "definition": [
       {
        "type": "text",
        "text": "LandX yapay zeka katmanının 3. seviyesi — ajanların kullanıcıya görünen yüzü."
       }
      ]
     },
     {
      "term": "Niçin?",
      "definition": [
       {
        "type": "text",
        "text": "Ajanın iş yapması için arayüzler lazım: belgeye eriş, akış başlat, bildirim gönder."
       }
      ]
     },
     {
      "term": "Nasıl?",
      "definition": [
       {
        "type": "text",
        "text": "6 modül — dosya, iş yönetimi, akış, bildirim, arama."
       }
      ]
     },
     {
      "term": "Nerede?",
      "definition": [
       {
        "type": "text",
        "text": "Ajan ile sistem arasındaki köprü."
       }
      ]
     },
     {
      "term": "Ne zaman?",
      "definition": [
       {
        "type": "text",
        "text": "Her ajan operasyonunun parçası."
       }
      ]
     },
     {
      "term": "Kim?",
      "definition": [
       {
        "type": "text",
        "text": "Geliştirici bağlar; ajan kullanır."
       }
      ]
     },
     {
      "term": "Analoji",
      "definition": [
       {
        "type": "text",
        "text": "Bir sekreterlik masası: ajan 'çalışan' olarak kullanır."
       }
      ]
     }
    ]
   }
  ]
 }
}